CHANGELOG.txt
LICENCE.txt
MANIFEST.in
README.txt
setup.py
DL_auto_cnn/__init__.py
DL_auto_cnn.egg-info/PKG-INFO
DL_auto_cnn.egg-info/SOURCES.txt
DL_auto_cnn.egg-info/dependency_links.txt
DL_auto_cnn.egg-info/requires.txt
DL_auto_cnn.egg-info/top_level.txt