Metadata-Version: 1.1
Name: DL-auto-cnn
Version: 0.0.1
Summary: creates a cnn architecture using user inputs
Home-page: UNKNOWN
Author: adil aziz
Author-email: adilaziz2013@gmail.com
License: MIT
Keywords: Deep Learning
Platform: UNKNOWN
Classifier: Development Status :: 5 - Production/Stable
Classifier: Intended Audience :: Education
Classifier: Operating System :: Microsoft :: Windows :: Windows 10
Classifier: License :: OSI Approved :: MIT License
Classifier: Programming Language :: Python :: 3
